ksom/__init__.py
ksom/ksom.py
ksom-0.9.3.dist-info/METADATA
ksom-0.9.3.dist-info/WHEEL
ksom-0.9.3.dist-info/licenses/LICENCE.txt
ksom-0.9.3.dist-info/RECORD
