Metadata-Version: 2.3
Name: ksom
Version: 0.9.3
Summary: Self Organising Maps in pytorch
Project-URL: Homepage, https://github.com/mdaquin/ksom
Project-URL: Issues, https://github.com/mdaquin/ksom/issues
Author-email: Mathieu d'Aquin <mathieu.daquin.w+ksom@gmail.com>
Classifier: License :: OSI Approved :: MIT License
Classifier: Operating System :: OS Independent
Classifier: Programming Language :: Python :: 3
Requires-Python: >=3.8
